datablender/__init__.py
datablender/base/__init__.py
datablender/base/connection.py
datablender/base/data.py
datablender/base/dataConfiguration.py
datablender/base/dataElement.py
datablender/base/dataLogging.py
datablender/base/directory.py
datablender/base/file.py
datablender/base/queryBuilder.py
datablender/base/request.py
datablender/base/text.py
datablender/base/web.py
datablender/data/__init__.py
datablender/data/asyncDataServer.py
datablender/data/asyncDataSourceCore.py
datablender/data/dataDirectory.py
datablender/data/dataFile.py
datablender/data/dataProcess.py
datablender/data/dataServer.py
datablender/data/dataSource.py
datablender/data/dataSourceCore.py
datablender/data/dataVersion.py
datablender/data/directoryElementController.py
datablender/data/filesTable.py
datablender/database/__init__.py
datablender/database/database.py
datablender/database/elementSQL.py
datablender/database/extension.py
datablender/database/function.py
datablender/database/role.py
datablender/database/schema.py
datablender/database/table.py
datablender/database/view.py
datablender/tests/__init__.py
datablender/tests/test_base.py
datablender/tests/test_data.py
datablender/tests/test_database.py
datablender-1.0.dist-info/METADATA
datablender-1.0.dist-info/WHEEL
datablender-1.0.dist-info/top_level.txt
datablender-1.0.dist-info/RECORD
