Metadata-Version: 2.1
Name: datablender
Version: 1.0
Summary: Tools for data.
Home-page: https://github.com/MontrealMobilite/datablender.git
Author: Julien Douville
Requires-Dist: sqlalchemy
Requires-Dist: psycopg2
Requires-Dist: datetime
Requires-Dist: numpy
Requires-Dist: pandas
Requires-Dist: dbf
Requires-Dist: openpyxl
Requires-Dist: beautifulsoup4
Requires-Dist: selenium
Requires-Dist: webdriver-manager
Requires-Dist: postgis
Requires-Dist: python-socketio
Requires-Dist: dbfread
Requires-Dist: scipy
Requires-Dist: scikit-learn
Requires-Dist: unidecode
Requires-Dist: geopandas
Requires-Dist: aiohttp
Requires-Dist: asyncpg
Provides-Extra: dev
Requires-Dist: pytest ; extra == 'dev'
Requires-Dist: build ; extra == 'dev'
Requires-Dist: twine ; extra == 'dev'
